hat_splitter-0.1.10.dist-info/METADATA
hat_splitter-0.1.10.dist-info/WHEEL
hat_splitter-0.1.10.dist-info/licenses/LICENSE
hat_splitter/__init__.py
hat_splitter/__init__.pyi
hat_splitter/py.typed
hat_splitter/hat_splitter.cpython-310-i386-linux-gnu.so
hat_splitter-0.1.10.dist-info/RECORD
