Metadata-Version: 2.4
Name: hat-splitter
Version: 0.1.10
Classifier: Programming Language :: Rust
Classifier: Programming Language :: Python :: Implementation :: CPython
Classifier: Programming Language :: Python :: Implementation :: PyPy
License-File: LICENSE
Summary: HAT splitter
Author: Michael Barlow <michael.barlow@aleph-alpha-ip.ai>
Author-email: Michael Barlow <michael.barlow@aleph-alpha-ip.ai>
Requires-Python: >=3.8
Project-URL: Source Code, https://github.com/Aleph-Alpha/hat-splitter
